tom_registration/__init__.py
tom_registration/admin.py
tom_registration/apps.py
tom_registration/middleware.py
tom_registration/migrations/__init__.py
tom_registration/models.py
tom_registration/registration_flows/approval_required/__init__.py
tom_registration/registration_flows/approval_required/forms.py
tom_registration/registration_flows/approval_required/urls.py
tom_registration/registration_flows/approval_required/views.py
tom_registration/registration_flows/open/__init__.py
tom_registration/registration_flows/open/forms.py
tom_registration/registration_flows/open/urls.py
tom_registration/registration_flows/open/views.py
tom_registration/templates/tom_registration/approve_user.html
tom_registration/templates/tom_registration/partials/pending_users.html
tom_registration/templates/tom_registration/partials/register_button.html
tom_registration/templates/tom_registration/register_user.html
tom_registration/templatetags/registration_extras.py
tom_registration/tests/__init__.py
tom_registration/tests/boot_django.py
tom_registration/tests/django_shell.py
tom_registration/tests/run_tests.py
tom_registration/tests/tests.py
tom_registration/tests/urls/__init__.py
tom_registration/tests/urls/test_urls.py
tom_registration-1.0.2.dist-info/LICENSE
tom_registration-1.0.2.dist-info/METADATA
tom_registration-1.0.2.dist-info/WHEEL
tom_registration-1.0.2.dist-info/RECORD
