Metadata-Version: 2.3
Name: tom-registration
Version: 1.0.2
Summary: Reusable TOMToolkit app to support multiple user registration flows.
License: GPL-3.0-only
Keywords: tomtoolkit,TOM,astronomy,astrophysics,cosmology,science
Author: TOM Toolkit Project
Author-email: tomtoolkit-maintainers@lco.global
Maintainer: Joey Chatelain
Maintainer-email: jchate6@gmail.com
Requires-Python: >=3.9.0,<3.13
Classifier: Environment :: Web Environment
Classifier: Framework :: Django
Classifier: Intended Audience :: Developers
Classifier: Intended Audience :: Science/Research
Classifier: License :: OSI Approved :: GNU General Public License v3 or later (GPLv3+)
Classifier: Operating System :: OS Independent
Classifier: Programming Language :: Python
Classifier: Programming Language :: Python :: 3
Classifier: Programming Language :: Python :: 3.9
Classifier: Programming Language :: Python :: 3.10
Classifier: Programming Language :: Python :: 3.11
Classifier: Programming Language :: Python :: 3.12
Classifier: Topic :: Scientific/Engineering :: Astronomy
Classifier: Topic :: Scientific/Engineering :: Physics
Requires-Dist: tomtoolkit (>=2.23.1,<3.0.0)
